evshow/__init__.py
evshow/__main__.py
evshow/_evshow.py
evshow/event2frame/__init__.py
evshow/event2frame/stacking.py
evshow/event2frame/concentration_net/__init__.py
evshow/event2frame/concentration_net/concentrate_events.onnx
evshow/event2frame/concentration_net/concentration_net.py
evshow/event2frame/e2vid/__init__.py
evshow/event2frame/e2vid/e2vid_net.onnx
evshow/event2frame/e2vid/e2vid_net.py
evshow/event2frame/e2vid/timers.py
evshow/event2frame/e2vid/utils.py
evshow/event2frame/shared/__init__.py
evshow/event2frame/shared/utils.py
evshow/readwrite/__init__.py
evshow/readwrite/_eventslicer.py
evshow/readwrite/base.py
evshow/readwrite/dsec.py
evshow-1.0.0.dist-info/METADATA
evshow-1.0.0.dist-info/WHEEL
evshow-1.0.0.dist-info/entry_points.txt
evshow-1.0.0.dist-info/licenses/LICENSE
evshow-1.0.0.dist-info/RECORD
