Metadata-Version: 2.3
Name: evshow
Version: 1.0.0
Summary: framerize and visualize event raw data
Author-email: Runiku Boa <bao@robot.t.u-tokyo.ac.jp>
License-File: LICENSE
Classifier: Programming Language :: Python :: 3
Requires-Python: >=3.7
